odoo10_addon_account_operating_unit-10.0.1.1.0-py2.7-nspkg.pth
odoo/addons/account_operating_unit/README.rst
odoo/addons/account_operating_unit/__init__.py
odoo/addons/account_operating_unit/__manifest__.py
odoo/addons/account_operating_unit/models/__init__.py
odoo/addons/account_operating_unit/models/account_journal.py
odoo/addons/account_operating_unit/models/account_move.py
odoo/addons/account_operating_unit/models/account_payment.py
odoo/addons/account_operating_unit/models/company.py
odoo/addons/account_operating_unit/models/invoice.py
odoo/addons/account_operating_unit/report/__init__.py
odoo/addons/account_operating_unit/report/account_invoice_report.py
odoo/addons/account_operating_unit/security/account_security.xml
odoo/addons/account_operating_unit/static/description/icon.png
odoo/addons/account_operating_unit/tests/__init__.py
odoo/addons/account_operating_unit/tests/test_account_operating_unit.py
odoo/addons/account_operating_unit/tests/test_cross_ou_journal_entry.py
odoo/addons/account_operating_unit/tests/test_invoice_operating_unit.py
odoo/addons/account_operating_unit/tests/test_operating_unit_security.py
odoo/addons/account_operating_unit/tests/test_payment_operating_unit.py
odoo/addons/account_operating_unit/views/account_invoice_report_view.xml
odoo/addons/account_operating_unit/views/account_journal_view.xml
odoo/addons/account_operating_unit/views/account_move_view.xml
odoo/addons/account_operating_unit/views/account_payment_view.xml
odoo/addons/account_operating_unit/views/company_view.xml
odoo/addons/account_operating_unit/views/invoice_view.xml
odoo/addons/account_operating_unit/views/report_agedpartnerbalance.xml
odoo/addons/account_operating_unit/views/report_financial.xml
odoo/addons/account_operating_unit/views/report_trialbalance.xml
odoo/addons/account_operating_unit/wizard/__init__.py
odoo/addons/account_operating_unit/wizard/account_financial_report.py
odoo10_addon_account_operating_unit-10.0.1.1.0.dist-info/DESCRIPTION.rst
odoo10_addon_account_operating_unit-10.0.1.1.0.dist-info/METADATA
odoo10_addon_account_operating_unit-10.0.1.1.0.dist-info/RECORD
odoo10_addon_account_operating_unit-10.0.1.1.0.dist-info/WHEEL
odoo10_addon_account_operating_unit-10.0.1.1.0.dist-info/metadata.json
odoo10_addon_account_operating_unit-10.0.1.1.0.dist-info/namespace_packages.txt
odoo10_addon_account_operating_unit-10.0.1.1.0.dist-info/top_level.txt
