Metadata-Version: 2.0
Name: odoo10-addon-account-operating-unit
Version: 10.0.1.1.0
Summary: Introduces Operating Unit fields in invoices and Accounting Entries with clearing account
Home-page: https://github.com/OCA/operating-unit
Author: Eficent, Serpent Consulting Services Pvt. Ltd.,Odoo Community Association (OCA)
Author-email: support@odoo-community.org
License: LGPL-3
Platform: UNKNOWN
Classifier: Programming Language :: Python
Classifier: Framework :: Odoo
Classifier: License :: OSI Approved :: GNU Lesser General Public License v3 (LGPLv3)
Requires-Python: ~=2.7
Requires-Dist: odoo (<10.1dev,>=10.0)
Requires-Dist: odoo10-addon-analytic-operating-unit
Requires-Dist: odoo10-addon-operating-unit
